chatbot/__init__.py
chatbot/client.py
chatbot/enums.py
chatbot/http_client.py
chatbot/__pycache__/__init__.cpython-38.pyc
chatbot/__pycache__/client.cpython-38.pyc
chatbot/__pycache__/enums.cpython-38.pyc
chatbot/__pycache__/http_client.cpython-38.pyc
chatbot/api/__init__.py
chatbot/api/audio.py
chatbot/api/file.py
chatbot/api/image.py
chatbot/api/interactive.py
chatbot/api/media.py
chatbot/api/post.py
chatbot/api/share_chat.py
chatbot/api/sticker.py
chatbot/api/text.py
chatbot/api/__pycache__/__init__.cpython-38.pyc
chatbot/api/__pycache__/audio.cpython-38.pyc
chatbot/api/__pycache__/file.cpython-38.pyc
chatbot/api/__pycache__/image.cpython-38.pyc
chatbot/api/__pycache__/interactive.cpython-38.pyc
chatbot/api/__pycache__/media.cpython-38.pyc
chatbot/api/__pycache__/post.cpython-38.pyc
chatbot/api/__pycache__/share_chat.cpython-38.pyc
chatbot/api/__pycache__/sticker.cpython-38.pyc
chatbot/api/__pycache__/text.cpython-38.pyc
feishu_chatbot-0.0.5.dist-info/METADATA
feishu_chatbot-0.0.5.dist-info/WHEEL
feishu_chatbot-0.0.5.dist-info/top_level.txt
feishu_chatbot-0.0.5.dist-info/RECORD
