Metadata-Version: 2.1
Name: feishu-chatbot
Version: 0.0.5
Summary: feishu chatbot api
Home-page: https://github.com/rexyan/feishu_chatbot
Author: RexYan
Author-email: rex_yan@126.com
License: MIT
Platform: all
Classifier: Development Status :: 4 - Beta
Classifier: Intended Audience :: Developers
Classifier: Topic :: Software Development :: Build Tools
Classifier: License :: OSI Approved :: MIT License
Classifier: Programming Language :: Python
Classifier: Programming Language :: Python :: 3.5
Classifier: Programming Language :: Python :: 3.6
Classifier: Programming Language :: Python :: 3.7
Classifier: Programming Language :: Python :: 3.8
Classifier: Programming Language :: Python :: 3.9
Requires-Dist: voluptuous (>=0.12.2)
Requires-Dist: requests (>=2.25.0)
